setup.py
mentions/__init__.py
mentions/mentions.py
mentions.egg-info/PKG-INFO
mentions.egg-info/SOURCES.txt
mentions.egg-info/dependency_links.txt
mentions.egg-info/not-zip-safe
mentions.egg-info/requires.txt
mentions.egg-info/top_level.txt