Metadata-Version: 1.0
Name: mentions
Version: 0.1.3
Summary: Get share counts from a given URL easily.
Home-page: https://github.com/thinkxl/mentions
Author: Juan Olvera
Author-email: thinkxl@gmail.com
License: MIT
Platform: UNKNOWN
